[
  {
    "src": "character-design/buizel x dachsbun.png",
    "category": "character-design"
  },
  {
    "src": "character-design/Darkrai + Typhlosion.png",
    "category": "character-design"
  },
  {
    "src": "character-design/Flareon + Ceruledge.png",
    "category": "character-design"
  },
  {
    "src": "character-design/Froslass + Jellicent.png",
    "category": "character-design"
  },
  {
    "src": "character-design/Garchomp + Barraskewda.png",
    "category": "character-design"
  },
  {
    "src": "character-design/gogoat + sawsbuck autumn.png",
    "category": "character-design"
  },
  {
    "src": "character-design/mega banette + serperior.png",
    "category": "character-design"
  },
  {
    "src": "character-design/Rockruff + Buneary.png",
    "category": "character-design"
  },
  {
    "src": "character-design/Shiny Furret + Sobble.png",
    "category": "character-design"
  },
  {
    "src": "character-design/Skitty + Slurpuff.png",
    "category": "character-design"
  },
  {
    "src": "character-design/Vaporeon + Aurorus.png",
    "category": "character-design"
  },
  {
    "src": "character-design/Vaporeon + Dhelmise.png",
    "category": "character-design"
  },
  {
    "src": "character-design/Basculegion + Feraligatr.png",
    "category": "character-design"
  },
  {
    "src": "character-design/Hisuian Decidueye + Honedge.png",
    "category": "character-design"
  },
  {
    "src": "character-design/Shiny Furret + Greninja.png",
    "category": "character-design"
  },
  {
    "src": "illustration/chocemi lps.png",
    "category": "illustration"
  },
  {
    "src": "illustration/fresa lps.png",
    "category": "illustration"
  },
  {
    "src": "illustration/nite.png",
    "category": "illustration"
  },
  {
    "src": "illustration/phyllo lps.png",
    "category": "illustration"
  },
  {
    "src": "illustration/remmi lps.png",
    "category": "illustration"
  },
  {
    "src": "illustration/viper lps.png",
    "category": "illustration"
  }
]